cli_task_manager/__init__.py
cli_task_manager/cli/__init__.py
cli_task_manager/cli/app.py
cli_task_manager/core/__init__.py
cli_task_manager/core/analytics.py
cli_task_manager/core/config.py
cli_task_manager/core/database.py
cli_task_manager/core/exporter.py
cli_task_manager/core/mobile.py
cli_task_manager/core/parser.py
cli_task_manager/core/security.py
cli_task_manager/core/sync.py
cli_task_manager/core/themes.py
cli_task_manager/daemon/__init__.py
cli_task_manager/daemon/main.py
cli_task_manager/models/__init__.py
cli_task_manager/models/dependency.py
cli_task_manager/models/project.py
cli_task_manager/models/reminder.py
cli_task_manager/models/tag.py
cli_task_manager/models/task.py
cli_task_manager/utils/__init__.py
cli_task_manager/utils/formatters.py
cli_task_manager/utils/validators.py
talkdo-1.0.0.dist-info/licenses/LICENSE
talkdo-1.0.0.dist-info/METADATA
talkdo-1.0.0.dist-info/WHEEL
talkdo-1.0.0.dist-info/entry_points.txt
talkdo-1.0.0.dist-info/top_level.txt
talkdo-1.0.0.dist-info/RECORD
