Metadata-Version: 2.4
Name: talkdo
Version: 1.0.0
Summary: Talkdo - Talk your to-dos. A professional CLI task manager with natural language processing
Author-email: Talkdo Team <team@talkdo.dev>
Maintainer-email: Talkdo Team <team@talkdo.dev>
License: MIT
Project-URL: Homepage, https://github.com/talkdo/talkdo
Project-URL: Repository, https://github.com/talkdo/talkdo
Project-URL: Documentation, https://talkdo.readthedocs.io
Project-URL: Bug Tracker, https://github.com/talkdo/talkdo/issues
Keywords: cli,task-manager,productivity,natural-language,todo,talkdo,voice,speech
Classifier: Development Status :: 5 - Production/Stable
Classifier: Intended Audience :: End Users/Desktop
Classifier: License :: OSI Approved :: MIT License
Classifier: Operating System :: OS Independent
Classifier: Programming Language :: Python :: 3
Classifier: Programming Language :: Python :: 3.8
Classifier: Programming Language :: Python :: 3.9
Classifier: Programming Language :: Python :: 3.10
Classifier: Programming Language :: Python :: 3.11
Classifier: Programming Language :: Python :: 3.12
Classifier: Topic :: Office/Business
Classifier: Topic :: Utilities
Requires-Python: >=3.8
License-File: LICENSE
Requires-Dist: typer[all]>=0.9.0
Requires-Dist: rich>=13.0.0
Requires-Dist: pydantic>=2.0.0
Requires-Dist: sqlalchemy>=2.0.0
Requires-Dist: dateparser>=1.1.0
Requires-Dist: pyyaml>=6.0
Requires-Dist: croniter>=1.3.0
Requires-Dist: plyer>=2.1.0
Requires-Dist: click>=8.0.0
Requires-Dist: tabulate>=0.9.0
Requires-Dist: python-dateutil>=2.8.0
Requires-Dist: schedule>=1.2.0
Requires-Dist: psutil>=5.9.0
Requires-Dist: qrcode>=7.4.0
Requires-Dist: cryptography>=41.0.0
Requires-Dist: requests>=2.31.0
Requires-Dist: pillow>=10.0.0
Provides-Extra: dev
Requires-Dist: pytest>=7.0.0; extra == "dev"
Requires-Dist: pytest-cov>=4.0.0; extra == "dev"
Requires-Dist: pytest-mock>=3.10.0; extra == "dev"
Requires-Dist: black>=23.0.0; extra == "dev"
Requires-Dist: isort>=5.12.0; extra == "dev"
Requires-Dist: flake8>=6.0.0; extra == "dev"
Requires-Dist: mypy>=1.0.0; extra == "dev"
Requires-Dist: pre-commit>=3.0.0; extra == "dev"
Dynamic: license-file
